hoot/ToyTestA.osm
hoot/ToyTestB.osm
hoot/__init__.py
hoot/__main__.py
hoot/hoot_pythonic.py
hoot/libpyhoot.so
hoot/utils.py
hoot/bin/HootEnv.sh
hoot/bin/RunHoot.sh
hoot/bin/hoot
hoot/bin/hoot.bin
hoot/bin/bearer/libqgenericbearer.a
hoot/bin/bearer/libqgenericbearer.prl
hoot/bin/generic/libqevdevkeyboardplugin.a
hoot/bin/generic/libqevdevkeyboardplugin.prl
hoot/bin/generic/libqevdevmouseplugin.a
hoot/bin/generic/libqevdevmouseplugin.prl
hoot/bin/generic/libqevdevtabletplugin.a
hoot/bin/generic/libqevdevtabletplugin.prl
hoot/bin/generic/libqevdevtouchplugin.a
hoot/bin/generic/libqevdevtouchplugin.prl
hoot/bin/generic/libqtuiotouchplugin.a
hoot/bin/generic/libqtuiotouchplugin.prl
hoot/bin/imageformats/libqgif.a
hoot/bin/imageformats/libqgif.prl
hoot/bin/imageformats/libqico.a
hoot/bin/imageformats/libqico.prl
hoot/bin/imageformats/libqjpeg.a
hoot/bin/imageformats/libqjpeg.prl
hoot/bin/platforminputcontexts/libcomposeplatforminputcontextplugin.a
hoot/bin/platforminputcontexts/libcomposeplatforminputcontextplugin.prl
hoot/bin/platforms/libqlinuxfb.a
hoot/bin/platforms/libqlinuxfb.prl
hoot/bin/platforms/libqminimal.a
hoot/bin/platforms/libqminimal.prl
hoot/bin/platforms/libqoffscreen.a
hoot/bin/platforms/libqoffscreen.prl
hoot/bin/platforms/libqvnc.a
hoot/bin/platforms/libqvnc.prl
hoot/bin/platforms/libqxcb.a
hoot/bin/platforms/libqxcb.prl
hoot/bin/sqldrivers/libqsqlite.a
hoot/bin/sqldrivers/libqsqlite.prl
hoot/conf/README
hoot/conf/hoot.json
hoot/conf/core/ApplyChangeset.conf
hoot/conf/core/AttributeConflation.conf
hoot/conf/core/AverageConflation.conf
hoot/conf/core/ConfigOptions.asciidoc
hoot/conf/core/DeriveChangeset.conf
hoot/conf/core/DifferentialConflation.conf
hoot/conf/core/GenericStats.json
hoot/conf/core/GeometryModifierRules.json
hoot/conf/core/GrailIngest.conf
hoot/conf/core/HorizontalConflation.conf
hoot/conf/core/Import.conf
hoot/conf/core/NetworkAlgorithm.conf
hoot/conf/core/NodeExport.conf
hoot-0.2.64.14.dist-info/LICENSE
hoot-0.2.64.14.dist-info/METADATA
hoot-0.2.64.14.dist-info/WHEEL
hoot-0.2.64.14.dist-info/top_level.txt
hoot-0.2.64.14.dist-info/RECORD
