Metadata-Version: 2.1
Name: hoot
Version: 0.2.64.14
Summary: This is an unofficial wrapper of Hootenanny
Home-page: https://github.com/epochgeo/pyhoot
Author: Jason R. Surratt
Author-email: jason@epochgeo.com
License: "GPLv3+"
Project-URL: Bug Tracker, https://github.com/epochgeo/pyhoot/issues
Platform: manylinux2014
Classifier: Programming Language :: Python :: 3
Classifier: Development Status :: 2 - Pre-Alpha
Classifier: License :: OSI Approved :: GNU General Public License v3 or later (GPLv3+)
Classifier: Operating System :: POSIX :: Linux
Requires-Python: >=3.7
License-File: LICENSE
Provides-Extra: dev
Requires-Dist: setuptools ; extra == 'dev'
Requires-Dist: auditwheel ; extra == 'dev'
Requires-Dist: sphinx ; extra == 'dev'
Requires-Dist: sphinx-markdown-builder ; extra == 'dev'
Requires-Dist: sphinx-autodoc-typehints ; extra == 'dev'
Requires-Dist: conan ; extra == 'dev'
Requires-Dist: build ; extra == 'dev'
Requires-Dist: twine ; extra == 'dev'
Requires-Dist: pydoc-markdown ; extra == 'dev'
